digitalocean/__init__.py
digitalocean/action.py
digitalocean/base.py
digitalocean/droplet.py
digitalocean_api_python-0.1.4.dist-info/METADATA
digitalocean_api_python-0.1.4.dist-info/WHEEL
digitalocean_api_python-0.1.4.dist-info/top_level.txt
digitalocean_api_python-0.1.4.dist-info/RECORD
